<?xml version="1.0" encoding="UTF-8"?>
<resource name="track.download">
  <request method="POST" url="tracks/:id/download.xml" login_required="true">
    <param name="id" type="integer" required="true"/>
    <param name="is_counted" type="boolean" required="false" default="true"/>
  </request>
  <response name="response" type="anchor">
    <element name="player_creation" type="anchor">
      <attribute name="ai" type="boolean"/>
      <attribute name="associated_item_ids" type="string"/>
      <attribute name="auto_reset" type="boolean"/>
      <attribute name="auto_tags" type="string"/>
      <attribute name="battle_friendly_fire" type="boolean"/>
      <attribute name="battle_kill_count" type="integer"/>
      <attribute name="battle_time_limit" type="integer"/>
      <attribute name="coolness" type="float"/>
      <attribute name="created_at" type="datetime"/>
      <attribute name="data_md5" type="string"/>
      <attribute name="data_size" type="integer"/>
      <attribute name="description" type="string"/>
      <attribute name="difficulty" type="string"/>
      <attribute name="first_published" type="datetime"/>
      <attribute name="hearts" type="integer"/>
      <attribute name="id" type="integer"/>
      <attribute name="is_remixable" type="boolean"/>
      <attribute name="last_published" type="datetime"/>
      <attribute name="level_mode" type="integer"/>
      <attribute name="longest_drift" type="float"/>
      <attribute name="longest_hang_time" type="float"/>
      <attribute name="moderation_status" type="string"/>
      <attribute name="name" type="string"/>
      <attribute name="num_laps" type="integer"/>
      <attribute name="num_racers" type="integer"/>
      <attribute name="player_creation_type" type="string"/>
      <attribute name="player_id" type="integer"/>
      <attribute name="preview_md5" type="string"/>
      <attribute name="preview_size" type="integer"/>
      <attribute name="race_type" type="string"/>
      <attribute name="races_finished" type="integer"/>
      <attribute name="races_started" type="integer"/>
      <attribute name="races_started_this_month" type="integer"/>
      <attribute name="races_started_this_week" type="integer"/>
      <attribute name="races_won" type="integer"/>
      <attribute name="rating_down" type="integer"/>
      <attribute name="rating_up" type="integer"/>
      <attribute name="scoreboard_mode" type="integer"/>
      <attribute name="speed" type="string"/>
      <attribute name="tags" type="string"/>
      <attribute name="track_theme" type="integer"/>
      <attribute name="unique_racer_count" type="integer"/>
      <attribute name="updated_at" type="datetime"/>
      <attribute name="user_tags" type="string"/>
      <attribute name="username" type="string"/>
      <attribute name="version" type="integer"/>
      <attribute name="votes" type="integer"/>
      <attribute name="weapon_set" type="string"/>
    </element>
  </response>
</resource>
